{
  "projectRoot": "/Users/inspius/Desktop/Porojet/github.com/battle-squad",
  "batchFiles": [
    {"path": "cmd/api/main.go", "language": "go", "sizeLines": 246, "fileCategory": "code"},
    {"path": "internal/api/appconfig/model.go", "language": "go", "sizeLines": 24, "fileCategory": "code"},
    {"path": "internal/api/auth/model.go", "language": "go", "sizeLines": 59, "fileCategory": "code"},
    {"path": "internal/api/auth/service.go", "language": "go", "sizeLines": 246, "fileCategory": "code"},
    {"path": "internal/api/character/model.go", "language": "go", "sizeLines": 109, "fileCategory": "code"},
    {"path": "internal/api/character/service.go", "language": "go", "sizeLines": 165, "fileCategory": "code"},
    {"path": "internal/api/economy/model.go", "language": "go", "sizeLines": 14, "fileCategory": "code"},
    {"path": "internal/api/economy/repository.go", "language": "go", "sizeLines": 123, "fileCategory": "code"},
    {"path": "internal/api/economy/service.go", "language": "go", "sizeLines": 55, "fileCategory": "code"},
    {"path": "internal/api/giftcode/model.go", "language": "go", "sizeLines": 29, "fileCategory": "code"},
    {"path": "internal/api/giftcode/service.go", "language": "go", "sizeLines": 110, "fileCategory": "code"},
    {"path": "internal/api/iap/model.go", "language": "go", "sizeLines": 32, "fileCategory": "code"},
    {"path": "internal/api/iap/service.go", "language": "go", "sizeLines": 128, "fileCategory": "code"},
    {"path": "internal/api/inventory/handler.go", "language": "go", "sizeLines": 40, "fileCategory": "code"},
    {"path": "internal/api/inventory/model.go", "language": "go", "sizeLines": 23, "fileCategory": "code"},
    {"path": "internal/api/inventory/repository.go", "language": "go", "sizeLines": 160, "fileCategory": "code"},
    {"path": "internal/api/inventory/service.go", "language": "go", "sizeLines": 15, "fileCategory": "code"},
    {"path": "internal/api/matchhistory/model.go", "language": "go", "sizeLines": 14, "fileCategory": "code"},
    {"path": "internal/api/matchhistory/service.go", "language": "go", "sizeLines": 15, "fileCategory": "code"},
    {"path": "internal/api/mission/model.go", "language": "go", "sizeLines": 33, "fileCategory": "code"},
    {"path": "internal/api/mission/service.go", "language": "go", "sizeLines": 80, "fileCategory": "code"},
    {"path": "internal/api/moderation/model.go", "language": "go", "sizeLines": 48, "fileCategory": "code"},
    {"path": "internal/api/player/model.go", "language": "go", "sizeLines": 24, "fileCategory": "code"},
    {"path": "internal/api/player/service.go", "language": "go", "sizeLines": 49, "fileCategory": "code"},
    {"path": "internal/api/rank/model.go", "language": "go", "sizeLines": 38, "fileCategory": "code"},
    {"path": "internal/api/rank/service.go", "language": "go", "sizeLines": 210, "fileCategory": "code"},
    {"path": "internal/api/rooms/model.go", "language": "go", "sizeLines": 12, "fileCategory": "code"},
    {"path": "internal/api/shop/model.go", "language": "go", "sizeLines": 32, "fileCategory": "code"},
    {"path": "internal/api/shop/service.go", "language": "go", "sizeLines": 158, "fileCategory": "code"},
    {"path": "internal/game/match/reward.go", "language": "go", "sizeLines": 456, "fileCategory": "code"},
    {"path": "internal/shared/auth/jwt.go", "language": "go", "sizeLines": 74, "fileCategory": "code"},
    {"path": "internal/shared/idempotency/idempotency.go", "language": "go", "sizeLines": 41, "fileCategory": "code"},
    {"path": "internal/shared/middleware/auth.go", "language": "go", "sizeLines": 43, "fileCategory": "code"},
    {"path": "internal/shared/middleware/ratelimit.go", "language": "go", "sizeLines": 90, "fileCategory": "code"}
  ],
  "batchImportData": {
    "cmd/api/main.go": ["internal/api/appconfig/handler.go", "internal/api/appconfig/model.go", "internal/api/appconfig/service.go", "internal/api/auth/handler.go", "internal/api/auth/model.go", "internal/api/auth/repository.go", "internal/api/auth/service.go", "internal/api/character/handler.go", "internal/api/character/model.go", "internal/api/character/repository.go", "internal/api/character/service.go", "internal/api/dev/handler.go", "internal/api/economy/model.go", "internal/api/economy/repository.go", "internal/api/economy/service.go", "internal/api/giftcode/handler.go", "internal/api/giftcode/model.go", "internal/api/giftcode/repository.go", "internal/api/giftcode/service.go", "internal/api/iap/handler.go", "internal/api/iap/model.go", "internal/api/iap/repository.go", "internal/api/iap/service.go", "internal/api/inventory/handler.go", "internal/api/inventory/model.go", "internal/api/inventory/repository.go", "internal/api/inventory/service.go", "internal/api/matchhistory/handler.go", "internal/api/matchhistory/model.go", "internal/api/matchhistory/repository.go", "internal/api/matchhistory/service.go", "internal/api/mission/handler.go", "internal/api/mission/model.go", "internal/api/mission/repository.go", "internal/api/mission/service.go", "internal/api/moderation/handler.go", "internal/api/moderation/model.go", "internal/api/moderation/repository.go", "internal/api/moderation/service.go", "internal/api/player/handler.go", "internal/api/player/model.go", "internal/api/player/repository.go", "internal/api/player/service.go", "internal/api/rank/handler.go", "internal/api/rank/model.go", "internal/api/rank/repository.go", "internal/api/rank/service.go", "internal/api/rooms/handler.go", "internal/api/rooms/model.go", "internal/api/shop/handler.go", "internal/api/shop/model.go", "internal/api/shop/repository.go", "internal/api/shop/service.go", "internal/shared/auth/jwt.go", "internal/shared/config/config.go", "internal/shared/database/postgres.go", "internal/shared/database/redis.go", "internal/shared/idempotency/idempotency.go", "internal/shared/middleware/auth.go", "internal/shared/middleware/correlation.go", "internal/shared/middleware/ratelimit.go", "internal/shared/middleware/version_check.go", "internal/shared/observability/health.go", "internal/shared/observability/logger.go", "internal/shared/observability/metrics.go"],
    "internal/api/appconfig/model.go": [],
    "internal/api/auth/model.go": [],
    "internal/api/auth/service.go": ["internal/shared/auth/jwt.go", "internal/shared/database/postgres.go", "internal/shared/database/redis.go"],
    "internal/api/character/model.go": [],
    "internal/api/character/service.go": ["internal/api/economy/model.go", "internal/api/economy/repository.go", "internal/api/economy/service.go", "internal/shared/database/postgres.go", "internal/shared/database/redis.go", "internal/shared/model/errors.go"],
    "internal/api/economy/model.go": [],
    "internal/api/economy/repository.go": [],
    "internal/api/economy/service.go": ["internal/shared/database/postgres.go", "internal/shared/database/redis.go"],
    "internal/api/giftcode/model.go": [],
    "internal/api/giftcode/service.go": ["internal/api/economy/model.go", "internal/api/economy/repository.go", "internal/api/economy/service.go", "internal/api/inventory/handler.go", "internal/api/inventory/model.go", "internal/api/inventory/repository.go", "internal/api/inventory/service.go", "internal/shared/database/postgres.go", "internal/shared/database/redis.go"],
    "internal/api/iap/model.go": [],
    "internal/api/iap/service.go": ["internal/api/economy/model.go", "internal/api/economy/repository.go", "internal/api/economy/service.go", "internal/shared/database/postgres.go", "internal/shared/database/redis.go"],
    "internal/api/inventory/handler.go": ["internal/shared/model/errors.go", "internal/shared/observability/health.go", "internal/shared/observability/logger.go", "internal/shared/observability/metrics.go"],
    "internal/api/inventory/model.go": [],
    "internal/api/inventory/repository.go": ["internal/shared/database/postgres.go", "internal/shared/database/redis.go"],
    "internal/api/inventory/service.go": [],
    "internal/api/matchhistory/model.go": [],
    "internal/api/matchhistory/service.go": [],
    "internal/api/mission/model.go": [],
    "internal/api/mission/service.go": ["internal/api/economy/model.go", "internal/api/economy/repository.go", "internal/api/economy/service.go", "internal/shared/database/postgres.go", "internal/shared/database/redis.go"],
    "internal/api/moderation/model.go": [],
    "internal/api/player/model.go": [],
    "internal/api/player/service.go": [],
    "internal/api/rank/model.go": [],
    "internal/api/rank/service.go": ["internal/api/economy/model.go", "internal/api/economy/repository.go", "internal/api/economy/service.go", "internal/shared/database/postgres.go", "internal/shared/database/redis.go"],
    "internal/api/rooms/model.go": [],
    "internal/api/shop/model.go": [],
    "internal/api/shop/service.go": ["internal/api/economy/model.go", "internal/api/economy/repository.go", "internal/api/economy/service.go", "internal/api/inventory/handler.go", "internal/api/inventory/model.go", "internal/api/inventory/repository.go", "internal/api/inventory/service.go", "internal/shared/database/postgres.go", "internal/shared/database/redis.go", "internal/shared/idempotency/idempotency.go"],
    "internal/game/match/reward.go": ["internal/api/economy/model.go", "internal/api/economy/repository.go", "internal/api/economy/service.go", "internal/shared/database/postgres.go", "internal/shared/database/redis.go"],
    "internal/shared/auth/jwt.go": [],
    "internal/shared/idempotency/idempotency.go": ["internal/shared/database/postgres.go", "internal/shared/database/redis.go"],
    "internal/shared/middleware/auth.go": ["internal/shared/auth/jwt.go", "internal/shared/model/errors.go", "internal/shared/observability/health.go", "internal/shared/observability/logger.go", "internal/shared/observability/metrics.go"],
    "internal/shared/middleware/ratelimit.go": ["internal/shared/model/errors.go"]
  }
}
